[
  {
    "title": "World War Z",
    "person": "Brad Pitt",
    "year": "2013",
    "type": "Movie",
    "description": "As the world is grasped by a mysterious infection that turns humans into zombies, Gerry, a former UN investigator has to leave his family to determine the source of the infection.",
    "id": 1765305949786
  },
  {
    "title": "Thrawn",
    "person": "Timothy Zahn",
    "year": "2017",
    "type": "Book",
    "description": "Thrawn's rise to Grand Admiral through sheer intellect, and Pryce's political navigation.",
    "id": 1765304990707
  },
  {
    "title": "Ahsoka",
    "person": "E. K. Johnston",
    "year": "2016",
    "type": "Book",
    "description": "Ahsoka realizes that choosing a side is inevitable.",
    "id": 1765631139874
  },
  {
    "title": "1",
    "person": "",
    "year": "",
    "description": "",
    "id": 1765659985812
  },
  {
    "title": "2",
    "person": "",
    "year": "",
    "description": "",
    "id": 1765659987196
  },
  {
    "title": "3",
    "person": "",
    "year": "",
    "description": "",
    "id": 1765659988543
  },
  {
    "title": "4",
    "person": "",
    "year": "",
    "description": "",
    "id": 1765659989737
  },
  {
    "title": "5",
    "person": "",
    "year": "",
    "description": "",
    "id": 1765659991411
  },
  {
    "title": "6",
    "person": "",
    "year": "",
    "description": "",
    "id": 1765659992854
  }
]